{"namedChunkGroups":{"polyfill":{"name":"polyfill","assets":[{"name":"webpack-runtime-5244d43f9b6fe43b5596.js","size":4595},{"name":"polyfill-b28af4caf62d8599825b.js","size":82641}],"filteredAssets":0,"assetsSize":87236,"filteredAuxiliaryAssets":2,"auxiliaryAssetsSize":219333},"app":{"name":"app","assets":[{"name":"webpack-runtime-5244d43f9b6fe43b5596.js","size":4595},{"name":"styles.9cab90d90c88285f442a.css","size":82005},{"name":"framework-d156a5d2cf06f46272e7.js","size":128888},{"name":"app-33dc408646786f50dc53.js","size":116806}],"filteredAssets":0,"assetsSize":332294,"filteredAuxiliaryAssets":3,"auxiliaryAssetsSize":853872},"component---src-pages-404-js":{"name":"component---src-pages-404-js","assets":[{"name":"styles.9cab90d90c88285f442a.css","size":82005},{"name":"commons-dfc58e54f6d85bc4d1dc.js","size":56093},{"name":"component---src-pages-404-js-fb98d48337f5c37c62de.js","size":430}],"filteredAssets":0,"assetsSize":138528,"filteredAuxiliaryAssets":2,"auxiliaryAssetsSize":193718},"component---src-pages-index-js":{"name":"component---src-pages-index-js","assets":[{"name":"styles.9cab90d90c88285f442a.css","size":82005},{"name":"commons-dfc58e54f6d85bc4d1dc.js","size":56093},{"name":"component---src-pages-index-js-35cbe1074b61a4d079c6.js","size":4241}],"filteredAssets":0,"assetsSize":142339,"filteredAuxiliaryAssets":2,"auxiliaryAssetsSize":202272},"component---src-pages-services-js":{"name":"component---src-pages-services-js","assets":[{"name":"styles.9cab90d90c88285f442a.css","size":82005},{"name":"commons-dfc58e54f6d85bc4d1dc.js","size":56093},{"name":"component---src-pages-services-js-0cbaba61ebfc72391205.js","size":1090}],"filteredAssets":0,"assetsSize":139188,"filteredAuxiliaryAssets":2,"auxiliaryAssetsSize":196151},"component---src-pages-team-js":{"name":"component---src-pages-team-js","assets":[{"name":"styles.9cab90d90c88285f442a.css","size":82005},{"name":"commons-dfc58e54f6d85bc4d1dc.js","size":56093},{"name":"component---src-pages-team-js-96187fade07f01d4d074.js","size":5202}],"filteredAssets":0,"assetsSize":143300,"filteredAuxiliaryAssets":2,"auxiliaryAssetsSize":203302},"component---src-templates-service-js":{"name":"component---src-templates-service-js","assets":[{"name":"styles.9cab90d90c88285f442a.css","size":82005},{"name":"commons-dfc58e54f6d85bc4d1dc.js","size":56093},{"name":"component---src-templates-service-js-db15cc53c81710ee538f.js","size":782}],"filteredAssets":0,"assetsSize":138880,"filteredAuxiliaryAssets":2,"auxiliaryAssetsSize":194690},"component---src-templates-team-js":{"name":"component---src-templates-team-js","assets":[{"name":"styles.9cab90d90c88285f442a.css","size":82005},{"name":"commons-dfc58e54f6d85bc4d1dc.js","size":56093},{"name":"component---src-templates-team-js-32647c8d4d106cfe3137.js","size":776}],"filteredAssets":0,"assetsSize":138874,"filteredAuxiliaryAssets":2,"auxiliaryAssetsSize":194669}},"assetsByChunkName":{"polyfill":["webpack-runtime-5244d43f9b6fe43b5596.js","polyfill-b28af4caf62d8599825b.js"],"app":["webpack-runtime-5244d43f9b6fe43b5596.js","styles.9cab90d90c88285f442a.css","framework-d156a5d2cf06f46272e7.js","app-33dc408646786f50dc53.js"],"component---src-pages-404-js":["styles.9cab90d90c88285f442a.css","commons-dfc58e54f6d85bc4d1dc.js","component---src-pages-404-js-fb98d48337f5c37c62de.js"],"component---src-pages-index-js":["styles.9cab90d90c88285f442a.css","commons-dfc58e54f6d85bc4d1dc.js","component---src-pages-index-js-35cbe1074b61a4d079c6.js"],"component---src-pages-services-js":["styles.9cab90d90c88285f442a.css","commons-dfc58e54f6d85bc4d1dc.js","component---src-pages-services-js-0cbaba61ebfc72391205.js"],"component---src-pages-team-js":["styles.9cab90d90c88285f442a.css","commons-dfc58e54f6d85bc4d1dc.js","component---src-pages-team-js-96187fade07f01d4d074.js"],"component---src-templates-service-js":["styles.9cab90d90c88285f442a.css","commons-dfc58e54f6d85bc4d1dc.js","component---src-templates-service-js-db15cc53c81710ee538f.js"],"component---src-templates-team-js":["styles.9cab90d90c88285f442a.css","commons-dfc58e54f6d85bc4d1dc.js","component---src-templates-team-js-32647c8d4d106cfe3137.js"]},"childAssetsByChunkName":{}}