{"namedChunkGroups":{"polyfill":{"name":"polyfill","assets":[{"name":"webpack-runtime-b0051a403c1f317b567a.js","size":4595},{"name":"polyfill-b28af4caf62d8599825b.js","size":82641}],"filteredAssets":0,"assetsSize":87236,"filteredAuxiliaryAssets":2,"auxiliaryAssetsSize":219333},"app":{"name":"app","assets":[{"name":"webpack-runtime-b0051a403c1f317b567a.js","size":4595},{"name":"styles.aa50f150965918d4af09.css","size":82168},{"name":"framework-d156a5d2cf06f46272e7.js","size":128888},{"name":"app-3047cf6d700d50740009.js","size":117008}],"filteredAssets":0,"assetsSize":332659,"filteredAuxiliaryAssets":3,"auxiliaryAssetsSize":854839},"component---src-pages-404-js":{"name":"component---src-pages-404-js","assets":[{"name":"styles.aa50f150965918d4af09.css","size":82168},{"name":"commons-2da7fcd8170f6f5ad7a3.js","size":20568},{"name":"component---src-pages-404-js-fb98d48337f5c37c62de.js","size":430}],"filteredAssets":0,"assetsSize":103166,"filteredAuxiliaryAssets":2,"auxiliaryAssetsSize":81432},"component---src-pages-index-js":{"name":"component---src-pages-index-js","assets":[{"name":"styles.aa50f150965918d4af09.css","size":82168},{"name":"commons-2da7fcd8170f6f5ad7a3.js","size":20568},{"name":"component---src-pages-index-js-f1bae59aa2ad7f1ef773.js","size":2954}],"filteredAssets":0,"assetsSize":105690,"filteredAuxiliaryAssets":2,"auxiliaryAssetsSize":87849},"component---src-pages-services-js":{"name":"component---src-pages-services-js","assets":[{"name":"styles.aa50f150965918d4af09.css","size":82168},{"name":"commons-2da7fcd8170f6f5ad7a3.js","size":20568},{"name":"component---src-pages-services-js-0cbaba61ebfc72391205.js","size":1090}],"filteredAssets":0,"assetsSize":103826,"filteredAuxiliaryAssets":2,"auxiliaryAssetsSize":83865},"component---src-pages-team-js":{"name":"component---src-pages-team-js","assets":[{"name":"styles.aa50f150965918d4af09.css","size":82168},{"name":"commons-2da7fcd8170f6f5ad7a3.js","size":20568},{"name":"component---src-pages-team-js-f3a651b33c7f415ebf59.js","size":3011}],"filteredAssets":0,"assetsSize":105747,"filteredAuxiliaryAssets":2,"auxiliaryAssetsSize":87636},"component---src-templates-service-js":{"name":"component---src-templates-service-js","assets":[{"name":"styles.aa50f150965918d4af09.css","size":82168},{"name":"commons-2da7fcd8170f6f5ad7a3.js","size":20568},{"name":"component---src-templates-service-js-daacd301b42f9e99cde3.js","size":792}],"filteredAssets":0,"assetsSize":103528,"filteredAuxiliaryAssets":2,"auxiliaryAssetsSize":82442},"component---src-templates-team-js":{"name":"component---src-templates-team-js","assets":[{"name":"styles.aa50f150965918d4af09.css","size":82168},{"name":"commons-2da7fcd8170f6f5ad7a3.js","size":20568},{"name":"component---src-templates-team-js-32647c8d4d106cfe3137.js","size":776}],"filteredAssets":0,"assetsSize":103512,"filteredAuxiliaryAssets":2,"auxiliaryAssetsSize":82383}},"assetsByChunkName":{"polyfill":["webpack-runtime-b0051a403c1f317b567a.js","polyfill-b28af4caf62d8599825b.js"],"app":["webpack-runtime-b0051a403c1f317b567a.js","styles.aa50f150965918d4af09.css","framework-d156a5d2cf06f46272e7.js","app-3047cf6d700d50740009.js"],"component---src-pages-404-js":["styles.aa50f150965918d4af09.css","commons-2da7fcd8170f6f5ad7a3.js","component---src-pages-404-js-fb98d48337f5c37c62de.js"],"component---src-pages-index-js":["styles.aa50f150965918d4af09.css","commons-2da7fcd8170f6f5ad7a3.js","component---src-pages-index-js-f1bae59aa2ad7f1ef773.js"],"component---src-pages-services-js":["styles.aa50f150965918d4af09.css","commons-2da7fcd8170f6f5ad7a3.js","component---src-pages-services-js-0cbaba61ebfc72391205.js"],"component---src-pages-team-js":["styles.aa50f150965918d4af09.css","commons-2da7fcd8170f6f5ad7a3.js","component---src-pages-team-js-f3a651b33c7f415ebf59.js"],"component---src-templates-service-js":["styles.aa50f150965918d4af09.css","commons-2da7fcd8170f6f5ad7a3.js","component---src-templates-service-js-daacd301b42f9e99cde3.js"],"component---src-templates-team-js":["styles.aa50f150965918d4af09.css","commons-2da7fcd8170f6f5ad7a3.js","component---src-templates-team-js-32647c8d4d106cfe3137.js"]},"childAssetsByChunkName":{}}